ppconfig/__init__.py
ppconfig/__version__.py
ppconfig/ppconfig.py
ppconfig-1.0.3.dist-info/LICENSE.txt
ppconfig-1.0.3.dist-info/METADATA
ppconfig-1.0.3.dist-info/WHEEL
ppconfig-1.0.3.dist-info/top_level.txt
ppconfig-1.0.3.dist-info/RECORD
