Metadata-Version: 2.1
Name: ppconfig
Version: 1.0.3
Summary: Configuration helper
Home-page: https://github.com/peterpakos/ppconfig
Author: Peter Pakos
Author-email: peter.pakos@wandisco.com
License: GPLv3
Keywords: python project config configuration helper manager
Platform: UNKNOWN
Classifier: Programming Language :: Python :: 2
Classifier: Programming Language :: Python :: 2.7
Classifier: Programming Language :: Python :: 3
Classifier: Programming Language :: Python :: 3.4
Classifier: Programming Language :: Python :: 3.5
Classifier: Programming Language :: Python :: 3.6
Classifier: Programming Language :: Python :: 3.7
Classifier: License :: OSI Approved :: GNU General Public License v3 (GPLv3)
